linkinvclient
