Metadata-Version: 1.0
Name: linkinvclient
Version: 1.4.2
Summary: python  Client for accessing linkinv and lnet
Home-page: https://github.com/microservice-tsp-billing/linkinvclient
Author: Bhujay Kumar Bhatta
Author-email: bhujay.bhatta@yahoo.com
License: Apache Software License
Platform: UNKNOWN
